arg_ros_tools/__init__.py
arg_ros_tools/_modidx.py
arg_ros_tools/_nbdev.py
arg_ros_tools/camera_project.py
arg_ros_tools/core.py
arg_ros_tools/rosbag_tools.py
arg_ros_tools-0.0.2.dist-info/LICENSE
arg_ros_tools-0.0.2.dist-info/METADATA
arg_ros_tools-0.0.2.dist-info/WHEEL
arg_ros_tools-0.0.2.dist-info/top_level.txt
arg_ros_tools-0.0.2.dist-info/RECORD
