Metadata-Version: 2.1
Name: arg-ros-tools
Version: 0.0.2
Summary: A toolset for navigation(ex:rosbag) created by arg lab
Home-page: https://github.com/ARG-NCTU/arg_ros_tools/tree/master/
Author: hchengwang
Author-email: hchengwang@gmail.com
License: Apache Software License 2.0
Keywords: navi tools rosbag
Classifier: Development Status :: 3 - Alpha
Classifier: Intended Audience :: Developers
Classifier: Natural Language :: English
Classifier: Programming Language :: Python :: 3.6
Classifier: Programming Language :: Python :: 3.7
Classifier: Programming Language :: Python :: 3.8
Classifier: Programming Language :: Python :: 3.9
Classifier: Programming Language :: Python :: 3.10
Classifier: License :: OSI Approved :: Apache Software License
Requires-Python: >=3.6
License-File: LICENSE
Requires-Dist: pip
Requires-Dist: packaging
Provides-Extra: dev
